{
    "camera": 
    {
        "lookfrom": [0.0, 1.0, 7.0],
        "lookat":   [0.0, 0.0, 0.0],
        "fov":      100.0
    },
    "planes": [
        {
            "origin": [0.0, -2.0, 0.0],
            "normal": [0.0, 1.0, 0.0],
            "color":  [1.0, 1.0, 1.0],
            "mat": "flat"
        },
        {
            "origin": [0.0, 0.0, -5.0],
            "normal": [0.0, 0.0, 1.0],
            "color":  [1.0, 1.0, 1.0],
            "mat": "flat"
        },
        {
            "origin": [5.0, 0.0, 0.0],
            "normal": [-1.0, 0.0, 0.0],
            "color":  [1.0, 1.0, 1.0],
            "mat": "flat"
        },
        {
            "origin": [-5.0, 0.0, 0.0],
            "normal": [1.0, 0.0, 0.0],
            "color":  [1.0, 1.0, 1.0],
            "mat": "flat"
        },
        {
            "origin": [0.0, 10.0, 0.0],
            "normal": [0.0, -1.0, 0.0],
            "color":  [1.0, 1.0, 1.0],
            "mat": "flat"
        },
        {
            "origin": [0.0, 0.0, 7.0],
            "normal": [0.0, 0.0, -1.0],
            "color":  [1.0, 1.0, 1.0],
            "mat": "flat"
        }
    ],

    "spheres": [
        {
            "color":  [1.0, 1.0, 1.0],
            "radius": 1.0,
            "center": [0.0, 0.0, 0.0],
            "mat": "glass"
        },
        {
            "color":  [1.0, 1.0, 1.0],
            "radius": 1.5,
            "center": [0.0, 7.0, 0.0],
            "mat": "diffuse_light"
        }
    ]
}